ml_pca/__init__.py
ml_pca/text_reader.py
ml_pca/data/my_code.py
ml_pca-0.1.dist-info/METADATA
ml_pca-0.1.dist-info/WHEEL
ml_pca-0.1.dist-info/top_level.txt
ml_pca-0.1.dist-info/RECORD
